shafts/DL_dataset.py
shafts/DL_model.py
shafts/DL_model_tf.py
shafts/DL_module.py
shafts/DL_train.py
shafts/__init__.py
shafts/_env.py
shafts/dataset.py
shafts/inference.py
shafts/inference_gcloud.py
shafts/mathexpr.py
shafts/model.py
shafts/shaft_version.json
shafts/train.py
shafts/testCase/test_shaft.py
shafts/utils/GEE_Download_2021.csv
shafts/utils/GEE_Download_2021_case.csv
shafts/utils/GEE_ops.py
shafts/utils/HeightGen.csv
shafts/utils/HeightGen_back.csv
shafts/utils/README.md
shafts/utils/__init__.py
shafts/utils/ee_download.sh
shafts/utils/ee_ops.py
shafts/utils/gdal_ops.py
shafts/utils/postprocessing.py
shafts-2023.40.dist-info/METADATA
shafts-2023.40.dist-info/WHEEL
shafts-2023.40.dist-info/top_level.txt
shafts-2023.40.dist-info/RECORD
