Metadata-Version: 2.1
Name: shafts
Version: 2023.40
Summary: Simultaneous building Height And FootprinT extraction from Sentinel Imagery
Home-page: https://github.com/LllC-mmd/SHAFTS
Author: Ruidong LiDr Ting Sun, Prof Guangheng Ni
Author-email: lrd19@mails.tsinghua.edu.cn, ting.sun@reading.ac.uk, ghni@tsinghua.edu.cn
License: GPL-V3.0
Classifier: Programming Language :: Python :: 3.8
Classifier: Intended Audience :: Education
Classifier: Intended Audience :: Science/Research
Classifier: Operating System :: MacOS :: MacOS X
Classifier: Operating System :: Microsoft :: Windows
Classifier: Operating System :: POSIX :: Linux
Requires-Python: >=3.8
Requires-Dist: torch
Requires-Dist: torchvision
Requires-Dist: tensorflow
Requires-Dist: tensorflow-probability
Requires-Dist: gdal (>=3.0.0)
Requires-Dist: numpy
Requires-Dist: matplotlib
Requires-Dist: scipy
Requires-Dist: pandas
Requires-Dist: albumentations
Requires-Dist: scikit-learn
Requires-Dist: scikit-image
Requires-Dist: xgboost
Requires-Dist: h5py
Requires-Dist: shapely
Requires-Dist: geopandas
Requires-Dist: rasterio
Requires-Dist: lmdb
Requires-Dist: kneed
Requires-Dist: pyarrow
Requires-Dist: opencv-python
Requires-Dist: earthengine-api
Requires-Dist: gcloud
